evoml_api_models/__init__.py
evoml_api_models/graphs.py
evoml_api_models/optimisation.py
evoml_api_models/py.typed
evoml_api_models/string_enum.py
evoml_api_models/utils.py
evoml_api_models/api_models/__init__.py
evoml_api_models/api_models/evoml_worker_models.py
evoml_api_models/base/__init__.py
evoml_api_models/base/base_conf_types.py
evoml_api_models/base/base_data_types.py
evoml_api_models/builder/__init__.py
evoml_api_models/builder/builder.py
evoml_api_models/builder/interface.py
evoml_api_models/converter/__init__.py
evoml_api_models/converter/abstract_factory.py
evoml_api_models/converter/highcharts/__init__.py
evoml_api_models/converter/highcharts/acf.py
evoml_api_models/converter/highcharts/aggregation_barchart.py
evoml_api_models/converter/highcharts/auc.py
evoml_api_models/converter/highcharts/barchart.py
evoml_api_models/converter/highcharts/box_violin.py
evoml_api_models/converter/highcharts/boxplot.py
evoml_api_models/converter/highcharts/calendar_plot.py
evoml_api_models/converter/highcharts/column.py
evoml_api_models/converter/highcharts/confusion_matrix.py
evoml_api_models/converter/highcharts/data.py
evoml_api_models/converter/highcharts/error_bar.py
evoml_api_models/converter/highcharts/heatmap.py
evoml_api_models/converter/highcharts/histogram.py
evoml_api_models/converter/highcharts/interface.py
evoml_api_models/converter/highcharts/kde.py
evoml_api_models/converter/highcharts/line.py
evoml_api_models/converter/highcharts/line_histogram.py
evoml_api_models/converter/highcharts/mapbubble.py
evoml_api_models/converter/highcharts/parallel_plot.py
evoml_api_models/converter/highcharts/scatter.py
evoml_api_models/converter/highcharts/time_series.py
evoml_api_models/converter/highcharts/timeline.py
evoml_api_models/converter/highcharts/tooltip.py
evoml_api_models/converter/highcharts/utils.py
evoml_api_models/converter/highcharts/violin.py
evoml_api_models/converter/highcharts/waterfall.py
evoml_api_models/converter/highcharts/wordcloud.py
turintech_evoml_api_models-3.2.0.dist-info/LICENSE
turintech_evoml_api_models-3.2.0.dist-info/METADATA
turintech_evoml_api_models-3.2.0.dist-info/WHEEL
turintech_evoml_api_models-3.2.0.dist-info/top_level.txt
turintech_evoml_api_models-3.2.0.dist-info/RECORD
